timepkg/__init__.py
timepkg/guardian.py
timepkg/keeper.py
timepkg/validation.py
timepkg-0.3.2.dist-info/LICENSE
timepkg-0.3.2.dist-info/METADATA
timepkg-0.3.2.dist-info/WHEEL
timepkg-0.3.2.dist-info/RECORD
